drd/.gitignore
drd/__init__.py
drd/api/__init__.py
drd/api/claude_api.py
drd/api/main.py
drd/api/ollama_api.py
drd/api/openai_api.py
drd/cli/__init__.py
drd/cli/ask_handler.py
drd/cli/commands.py
drd/cli/main.py
drd/cli/monitor/__init__.py
drd/cli/monitor/error_resolver.py
drd/cli/monitor/history_tracker.py
drd/cli/monitor/input_handler.py
drd/cli/monitor/input_parser.py
drd/cli/monitor/main.py
drd/cli/monitor/output_monitor.py
drd/cli/monitor/server_monitor.py
drd/cli/monitor/state.py
drd/cli/query/__init__.py
drd/cli/query/dynamic_command_handler.py
drd/cli/query/file_operations.py
drd/cli/query/image_handler.py
drd/cli/query/main.py
drd/main.py
drd/metadata/__init__.py
drd/metadata/common_utils.py
drd/metadata/initializer.py
drd/metadata/project_metadata.py
drd/metadata/rate_limit_handler.py
drd/metadata/updater.py
drd/prompts/__init__.py
drd/prompts/error_related_files_prompt.py
drd/prompts/error_resolution_prompt.py
drd/prompts/file_metada_desc_prompts.py
drd/prompts/file_operations.py
drd/prompts/framework_prompts/main_frameworks_prompt.py
drd/prompts/framework_prompts/nextjs_prompt.py
drd/prompts/get_project_info_prompts.py
drd/prompts/instructions.py
drd/prompts/metadata_update_prompts.py
drd/prompts/monitor_error_resolution.py
drd/utils/__init__.py
drd/utils/apply_file_changes.py
drd/utils/diff.py
drd/utils/file_utils.py
drd/utils/input.py
drd/utils/loader.py
drd/utils/parser.py
drd/utils/pretty_print_stream.py
drd/utils/step_executor.py
drd/utils/utils.py
dravid-0.14.0.dist-info/LICENSE
dravid-0.14.0.dist-info/METADATA
dravid-0.14.0.dist-info/WHEEL
dravid-0.14.0.dist-info/entry_points.txt
dravid-0.14.0.dist-info/RECORD
