Metadata-Version: 2.1
Name: dravid
Version: 0.14.0
Summary: A CLI coding super-framework using AI
License: MIT
Author: Vysakh Sreenivasan
Author-email: srvysakh@gmail.com
Requires-Python: >=3.8,<4.0
Classifier: License :: OSI Approved :: MIT License
Classifier: Programming Language :: Python :: 3
Classifier: Programming Language :: Python :: 3.8
Classifier: Programming Language :: Python :: 3.9
Classifier: Programming Language :: Python :: 3.10
Classifier: Programming Language :: Python :: 3.11
Classifier: Programming Language :: Python :: 3.12
Requires-Dist: click (>=8.0.0,<9.0.0)
Requires-Dist: colorama (>=0.4.4,<0.5.0)
Requires-Dist: lxml (>=5.2.2,<6.0.0)
Requires-Dist: openai (>=1.35.15,<2.0.0)
Requires-Dist: python-dotenv (>=0.19.0,<0.20.0)
Requires-Dist: requests (>=2.25.0,<3.0.0)
